{"v":4,"entries":{"gamepad-css--docs":{"id":"gamepad-css--docs","title":"Gamepad.css","name":"Docs","importPath":"./src/stories/Configure.mdx","storiesImports":[],"type":"docs","tags":["unattached-mdx","docs"]},"platform-nintendo--docs":{"id":"platform-nintendo--docs","title":"Platform/Nintendo","name":"Docs","importPath":"./src/stories/Nintendo.stories.ts","type":"docs","tags":["autodocs","docs"],"storiesImports":[]},"platform-nintendo--a":{"type":"story","id":"platform-nintendo--a","name":"A","title":"Platform/Nintendo","importPath":"./src/stories/Nintendo.stories.ts","tags":["autodocs","story"]},"platform-nintendo--b":{"type":"story","id":"platform-nintendo--b","name":"B","title":"Platform/Nintendo","importPath":"./src/stories/Nintendo.stories.ts","tags":["autodocs","story"]},"platform-nintendo--x":{"type":"story","id":"platform-nintendo--x","name":"X","title":"Platform/Nintendo","importPath":"./src/stories/Nintendo.stories.ts","tags":["autodocs","story"]},"platform-nintendo--y":{"type":"story","id":"platform-nintendo--y","name":"Y","title":"Platform/Nintendo","importPath":"./src/stories/Nintendo.stories.ts","tags":["autodocs","story"]},"platform-nintendo--up":{"type":"story","id":"platform-nintendo--up","name":"Up","title":"Platform/Nintendo","importPath":"./src/stories/Nintendo.stories.ts","tags":["autodocs","story"]},"platform-nintendo--down":{"type":"story","id":"platform-nintendo--down","name":"Down","title":"Platform/Nintendo","importPath":"./src/stories/Nintendo.stories.ts","tags":["autodocs","story"]},"platform-nintendo--left":{"type":"story","id":"platform-nintendo--left","name":"Left","title":"Platform/Nintendo","importPath":"./src/stories/Nintendo.stories.ts","tags":["autodocs","story"]},"platform-nintendo--right":{"type":"story","id":"platform-nintendo--right","name":"Right","title":"Platform/Nintendo","importPath":"./src/stories/Nintendo.stories.ts","tags":["autodocs","story"]},"platform-nintendo--zl":{"type":"story","id":"platform-nintendo--zl","name":"ZL","title":"Platform/Nintendo","importPath":"./src/stories/Nintendo.stories.ts","tags":["autodocs","story"]},"platform-nintendo--zr":{"type":"story","id":"platform-nintendo--zr","name":"ZR","title":"Platform/Nintendo","importPath":"./src/stories/Nintendo.stories.ts","tags":["autodocs","story"]},"platform-nintendo--l":{"type":"story","id":"platform-nintendo--l","name":"L","title":"Platform/Nintendo","importPath":"./src/stories/Nintendo.stories.ts","tags":["autodocs","story"]},"platform-nintendo--r":{"type":"story","id":"platform-nintendo--r","name":"R","title":"Platform/Nintendo","importPath":"./src/stories/Nintendo.stories.ts","tags":["autodocs","story"]},"platform-nintendo--select":{"type":"story","id":"platform-nintendo--select","name":"Select","title":"Platform/Nintendo","importPath":"./src/stories/Nintendo.stories.ts","tags":["autodocs","story"]},"platform-nintendo--start":{"type":"story","id":"platform-nintendo--start","name":"Start","title":"Platform/Nintendo","importPath":"./src/stories/Nintendo.stories.ts","tags":["autodocs","story"]},"platform-playstation--docs":{"id":"platform-playstation--docs","title":"Platform/PlayStation","name":"Docs","importPath":"./src/stories/PlayStation.stories.ts","type":"docs","tags":["autodocs","docs"],"storiesImports":[]},"platform-playstation--cross":{"type":"story","id":"platform-playstation--cross","name":"Cross","title":"Platform/PlayStation","importPath":"./src/stories/PlayStation.stories.ts","tags":["autodocs","story"]},"platform-playstation--circle":{"type":"story","id":"platform-playstation--circle","name":"Circle","title":"Platform/PlayStation","importPath":"./src/stories/PlayStation.stories.ts","tags":["autodocs","story"]},"platform-playstation--square":{"type":"story","id":"platform-playstation--square","name":"Square","title":"Platform/PlayStation","importPath":"./src/stories/PlayStation.stories.ts","tags":["autodocs","story"]},"platform-playstation--triangle":{"type":"story","id":"platform-playstation--triangle","name":"Triangle","title":"Platform/PlayStation","importPath":"./src/stories/PlayStation.stories.ts","tags":["autodocs","story"]},"platform-playstation--up":{"type":"story","id":"platform-playstation--up","name":"Up","title":"Platform/PlayStation","importPath":"./src/stories/PlayStation.stories.ts","tags":["autodocs","story"]},"platform-playstation--down":{"type":"story","id":"platform-playstation--down","name":"Down","title":"Platform/PlayStation","importPath":"./src/stories/PlayStation.stories.ts","tags":["autodocs","story"]},"platform-playstation--left":{"type":"story","id":"platform-playstation--left","name":"Left","title":"Platform/PlayStation","importPath":"./src/stories/PlayStation.stories.ts","tags":["autodocs","story"]},"platform-playstation--right":{"type":"story","id":"platform-playstation--right","name":"Right","title":"Platform/PlayStation","importPath":"./src/stories/PlayStation.stories.ts","tags":["autodocs","story"]},"platform-playstation--l-1":{"type":"story","id":"platform-playstation--l-1","name":"L1","title":"Platform/PlayStation","importPath":"./src/stories/PlayStation.stories.ts","tags":["autodocs","story"]},"platform-playstation--r-1":{"type":"story","id":"platform-playstation--r-1","name":"R1","title":"Platform/PlayStation","importPath":"./src/stories/PlayStation.stories.ts","tags":["autodocs","story"]},"platform-playstation--l-2":{"type":"story","id":"platform-playstation--l-2","name":"L2","title":"Platform/PlayStation","importPath":"./src/stories/PlayStation.stories.ts","tags":["autodocs","story"]},"platform-playstation--r-2":{"type":"story","id":"platform-playstation--r-2","name":"R2","title":"Platform/PlayStation","importPath":"./src/stories/PlayStation.stories.ts","tags":["autodocs","story"]},"platform-playstation--l-3":{"type":"story","id":"platform-playstation--l-3","name":"L3","title":"Platform/PlayStation","importPath":"./src/stories/PlayStation.stories.ts","tags":["autodocs","story"]},"platform-playstation--r-3":{"type":"story","id":"platform-playstation--r-3","name":"R3","title":"Platform/PlayStation","importPath":"./src/stories/PlayStation.stories.ts","tags":["autodocs","story"]},"platform-playstation--select":{"type":"story","id":"platform-playstation--select","name":"Select","title":"Platform/PlayStation","importPath":"./src/stories/PlayStation.stories.ts","tags":["autodocs","story"]},"platform-playstation--start":{"type":"story","id":"platform-playstation--start","name":"Start","title":"Platform/PlayStation","importPath":"./src/stories/PlayStation.stories.ts","tags":["autodocs","story"]},"platform-xbox--docs":{"id":"platform-xbox--docs","title":"Platform/Xbox","name":"Docs","importPath":"./src/stories/Xbox.stories.ts","type":"docs","tags":["autodocs","docs"],"storiesImports":[]},"platform-xbox--a":{"type":"story","id":"platform-xbox--a","name":"A","title":"Platform/Xbox","importPath":"./src/stories/Xbox.stories.ts","tags":["autodocs","story"]},"platform-xbox--b":{"type":"story","id":"platform-xbox--b","name":"B","title":"Platform/Xbox","importPath":"./src/stories/Xbox.stories.ts","tags":["autodocs","story"]},"platform-xbox--x":{"type":"story","id":"platform-xbox--x","name":"X","title":"Platform/Xbox","importPath":"./src/stories/Xbox.stories.ts","tags":["autodocs","story"]},"platform-xbox--y":{"type":"story","id":"platform-xbox--y","name":"Y","title":"Platform/Xbox","importPath":"./src/stories/Xbox.stories.ts","tags":["autodocs","story"]},"platform-xbox--up":{"type":"story","id":"platform-xbox--up","name":"Up","title":"Platform/Xbox","importPath":"./src/stories/Xbox.stories.ts","tags":["autodocs","story"]},"platform-xbox--down":{"type":"story","id":"platform-xbox--down","name":"Down","title":"Platform/Xbox","importPath":"./src/stories/Xbox.stories.ts","tags":["autodocs","story"]},"platform-xbox--left":{"type":"story","id":"platform-xbox--left","name":"Left","title":"Platform/Xbox","importPath":"./src/stories/Xbox.stories.ts","tags":["autodocs","story"]},"platform-xbox--right":{"type":"story","id":"platform-xbox--right","name":"Right","title":"Platform/Xbox","importPath":"./src/stories/Xbox.stories.ts","tags":["autodocs","story"]},"platform-xbox--lb":{"type":"story","id":"platform-xbox--lb","name":"LB","title":"Platform/Xbox","importPath":"./src/stories/Xbox.stories.ts","tags":["autodocs","story"]},"platform-xbox--rb":{"type":"story","id":"platform-xbox--rb","name":"RB","title":"Platform/Xbox","importPath":"./src/stories/Xbox.stories.ts","tags":["autodocs","story"]},"platform-xbox--lt":{"type":"story","id":"platform-xbox--lt","name":"LT","title":"Platform/Xbox","importPath":"./src/stories/Xbox.stories.ts","tags":["autodocs","story"]},"platform-xbox--rt":{"type":"story","id":"platform-xbox--rt","name":"RT","title":"Platform/Xbox","importPath":"./src/stories/Xbox.stories.ts","tags":["autodocs","story"]},"platform-xbox--l-3":{"type":"story","id":"platform-xbox--l-3","name":"L3","title":"Platform/Xbox","importPath":"./src/stories/Xbox.stories.ts","tags":["autodocs","story"]},"platform-xbox--r-3":{"type":"story","id":"platform-xbox--r-3","name":"R3","title":"Platform/Xbox","importPath":"./src/stories/Xbox.stories.ts","tags":["autodocs","story"]}}}
